text2chem/__init__.py
text2chem/chemical_data.py
text2chem/chemical_structure.py
text2chem/constants.py
text2chem/data_structures.py
text2chem/parser_pipeline.py
text2chem/regex_parser.py
text2chem/utils.py
text2chem/core/default_processing.py
text2chem/core/formula_parser.py
text2chem/core/formula_processing.py
text2chem/postprocessing_tools/__init__.py
text2chem/postprocessing_tools/element_variables_processing.py
text2chem/postprocessing_tools/postprocessing_abc.py
text2chem/postprocessing_tools/stoichiometric_variables_processing.py
text2chem/postprocessing_tools/substitute_additives.py
text2chem/preprocessing_tools/__init__.py
text2chem/preprocessing_tools/additives_processing.py
text2chem/preprocessing_tools/chemical_name_processing.py
text2chem/preprocessing_tools/mixture_processing.py
text2chem/preprocessing_tools/phase_processing.py
text2chem/preprocessing_tools/preprocessing_abc.py
text2chem/preprocessing_tools/pubchem_preprocessing.py
text2chem/resources/acronyms_dictionary.json
text2chem/resources/ions_dictionary.json
text2chem/resources/terms_dictionary.json
text2chem-0.0.3.dist-info/LICENSE
text2chem-0.0.3.dist-info/METADATA
text2chem-0.0.3.dist-info/WHEEL
text2chem-0.0.3.dist-info/top_level.txt
text2chem-0.0.3.dist-info/RECORD
