Metadata-Version: 2.1
Name: text2chem
Version: 0.0.3
Summary: RegEx-based text parser that converts chemical terms and material entities into chemical datastructure.
Author-email: Ceder Research Group <cedergroup-ml-team@lbl.gov>
Maintainer-email: Luca Foppiano <lucanoro@duck.com>
License: MIT License
Project-URL: Homepage, https://github.com/lfoppiano/text2chem
Project-URL: Repository, https://github.com/lfoppiano/text2chem
Project-URL: Changelog, https://github.com/lfoppiano/text2chem/blob/main/CHANGELOG.md
License-File: LICENSE
